custom_logger/__init__.py
custom_logger_xzf8971-1.1.0.dist-info/LICENSE
custom_logger_xzf8971-1.1.0.dist-info/METADATA
custom_logger_xzf8971-1.1.0.dist-info/WHEEL
custom_logger_xzf8971-1.1.0.dist-info/top_level.txt
custom_logger_xzf8971-1.1.0.dist-info/RECORD
