Metadata-Version: 2.1
Name: custom-logger-xzf8971
Version: 1.1.0
Summary: Just a very simple wrapper to configure a thread safe logger.
Author-email: Zifeng <zifeng.xu@foxmail.com>
Project-URL: Homepage, https://github.com/xzf89718/custom-logger-xzf8971
Project-URL: Bug Tracker, https://github.com/xzf89718/custom-logger-xzf8971/issues
Classifier: Programming Language :: Python :: 3
Classifier: License :: OSI Approved :: MIT License
Classifier: Operating System :: OS Independent
Requires-Python: >=3
License-File: LICENSE
